odoo8_addon_l10n_br_account_banking_payment-8.0.1.0.0.99.dev19-py2.7-nspkg.pth
odoo8_addon_l10n_br_account_banking_payment-8.0.1.0.0.99.dev19.dist-info/DESCRIPTION.rst
odoo8_addon_l10n_br_account_banking_payment-8.0.1.0.0.99.dev19.dist-info/METADATA
odoo8_addon_l10n_br_account_banking_payment-8.0.1.0.0.99.dev19.dist-info/RECORD
odoo8_addon_l10n_br_account_banking_payment-8.0.1.0.0.99.dev19.dist-info/WHEEL
odoo8_addon_l10n_br_account_banking_payment-8.0.1.0.0.99.dev19.dist-info/metadata.json
odoo8_addon_l10n_br_account_banking_payment-8.0.1.0.0.99.dev19.dist-info/namespace_packages.txt
odoo8_addon_l10n_br_account_banking_payment-8.0.1.0.0.99.dev19.dist-info/top_level.txt
odoo_addons/l10n_br_account_banking_payment/README.rst
odoo_addons/l10n_br_account_banking_payment/__init__.py
odoo_addons/l10n_br_account_banking_payment/__openerp__.py
odoo_addons/l10n_br_account_banking_payment/i18n/pt_BR.po
odoo_addons/l10n_br_account_banking_payment/models/__init__.py
odoo_addons/l10n_br_account_banking_payment/models/account_move_line.py
odoo_addons/l10n_br_account_banking_payment/models/account_payment.py
odoo_addons/l10n_br_account_banking_payment/models/res_partner_bank.py
odoo_addons/l10n_br_account_banking_payment/static/description/icon.png
odoo_addons/l10n_br_account_banking_payment/tests/__init__.py
odoo_addons/l10n_br_account_banking_payment/tests/test_bank.py
odoo_addons/l10n_br_account_banking_payment/views/account_due_list.xml
odoo_addons/l10n_br_account_banking_payment/views/account_payment.xml
odoo_addons/l10n_br_account_banking_payment/wizard/__init__.py
odoo_addons/l10n_br_account_banking_payment/wizard/payment_order_create.py
odoo_addons/l10n_br_account_banking_payment/wizard/payment_order_create_view.xml
