Metadata-Version: 2.0
Name: odoo8-addon-l10n-br-account-banking-payment
Version: 8.0.1.0.0.99.dev19
Summary: Brazilian Banking - Debit and Payments Export Infrastructure
Home-page: https://github.com/odoo-brazil/odoo-brazil-banking
Author: KMEE, Odoo Community Association (OCA)
Author-email: support@odoo-community.org
License: AGPL-3
Platform: UNKNOWN
Classifier: Programming Language :: Python
Classifier: Framework :: Odoo
Classifier: License :: OSI Approved :: GNU Affero General Public License v3
Requires-Python: ~=2.7
Requires-Dist: odoo (<9.0a,>=8.0a)
Requires-Dist: odoo8-addon-account-banking-payment-export
Requires-Dist: odoo8-addon-account-due-list
Requires-Dist: odoo8-addon-l10n-br-account
